setup.py
bhyve/__init__.py
bhyve/bkeeper.py
bhyve/config.py
bhyve/serializable.py
bhyve/utils.py
bhyve/vm.py
bhyve.egg-info/PKG-INFO
bhyve.egg-info/SOURCES.txt
bhyve.egg-info/dependency_links.txt
bhyve.egg-info/not-zip-safe
bhyve.egg-info/requires.txt
bhyve.egg-info/top_level.txt
scripts/bkeep