Metadata-Version: 1.0
Name: bhyve
Version: 0.2.1
Summary: A tool for managing bhyve VM's, because libvirt doesn't do want I want it to
Home-page: https://github.com/ConnorDillon/bhyve
Author: Connor Dillon
Author-email: connor@cdillon.nl
License: GPLv3
Platform: UNKNOWN
